guideframe/__init__.py
guideframe/assembly.py
guideframe/audio.py
guideframe/scripts/install_dependencies.sh
guideframe/selenium.py
guideframe/utils.py
guideframe/video.py
guideframe-0.5.2.dist-info/METADATA
guideframe-0.5.2.dist-info/WHEEL
guideframe-0.5.2.dist-info/RECORD
