Metadata-Version: 2.3
Name: guideframe
Version: 0.5.2
Summary: A tool to generate reusable software walkthrough videos via  code.
License: MIT
Author: Pat O'Connor
Requires-Python: >=3.11
Classifier: License :: OSI Approved :: MIT License
Classifier: Programming Language :: Python :: 3
Classifier: Programming Language :: Python :: 3.11
Classifier: Programming Language :: Python :: 3.12
Classifier: Programming Language :: Python :: 3.13
Requires-Dist: ffmpeg-python (==0.2.0)
Requires-Dist: gtts (==2.5.4)
Requires-Dist: mutagen (==1.47.0)
Requires-Dist: selenium (==4.27.1)
